gui_dictionary/__init__.py
gui_dictionary/main.py
gui_dictionary/utils/__init__.py
gui_dictionary/utils/dictionary.py
gui_dictionary-0.1.1.dist-info/METADATA
gui_dictionary-0.1.1.dist-info/WHEEL
gui_dictionary-0.1.1.dist-info/entry_points.txt
gui_dictionary-0.1.1.dist-info/RECORD
